fedora_messaging_git_hook/__init__.py
fedora_messaging_git_hook/cli.py
fedora_messaging_git_hook/hook.py
fedora_messaging_git_hook-0.1.1.dist-info/METADATA
fedora_messaging_git_hook-0.1.1.dist-info/WHEEL
fedora_messaging_git_hook-0.1.1.dist-info/entry_points.txt
fedora_messaging_git_hook-0.1.1.dist-info/top_level.txt
fedora_messaging_git_hook-0.1.1.dist-info/RECORD
